drf_common_exceptions/__init__.py
drf_common_exceptions/exceptions.py
drf_common_exceptions-0.1.1.dist-info/WHEEL
drf_common_exceptions-0.1.1.dist-info/METADATA
drf_common_exceptions-0.1.1.dist-info/RECORD
